{
  "_class": "shapePath",
  "booleanOperation": -1,
  "do_objectID": "ACBA31C4-5D17-4544-A3C8-9ABC2C3E56C1",
  "edited": true,
  "exportOptions": {
    "_class": "exportOptions",
    "do_objectID": "28BA1651-407F-4C1F-AB6A-DDB2D74D9697",
    "exportFormats": [
    ],
    "includedLayerIds": [
    ],
    "layerOptions": 0,
    "shouldTrim": false
  },
  "frame": {
    "_class": "rect",
    "constrainProportions": false,
    "do_objectID": "A466980F-77AE-4708-89DB-4F2865DF7796",
    "height": 107.3046153846152,
    "width": 61.75076923076924,
    "x": 0,
    "y": 0
  },
  "isClosed": true,
  "isFlippedHorizontal": false,
  "isFlippedVertical": false,
  "isLocked": false,
  "isVisible": true,
  "layerListExpandedType": 0,
  "name": "Path",
  "nameIsFixed": false,
  "pointRadiusBehaviour": 1,
  "points": [
    {
      "_class": "curvePoint",
      "cornerRadius": 0,
      "curveFrom": "{5.2342318764673682e-05, 0.33330311546248453}",
      "curveMode": 1,
      "curveTo": "{5.2342318764673682e-05, 0.33330311546248453}",
      "hasCurveFrom": false,
      "hasCurveTo": false,
      "point": "{5.2342318764673682e-05, 0.33330311546248453}"
    },
    {
      "_class": "curvePoint",
      "cornerRadius": 0,
      "curveFrom": "{1, 0}",
      "curveMode": 1,
      "curveTo": "{1, 0}",
      "hasCurveFrom": false,
      "hasCurveTo": false,
      "point": "{1, 0}"
    },
    {
      "_class": "curvePoint",
      "cornerRadius": 0,
      "curveFrom": "{1, 0.66666666666666652}",
      "curveMode": 1,
      "curveTo": "{1, 0.66666666666666652}",
      "hasCurveFrom": false,
      "hasCurveTo": false,
      "point": "{1, 0.66666666666666652}"
    },
    {
      "_class": "curvePoint",
      "cornerRadius": 0,
      "curveFrom": "{0, 1}",
      "curveMode": 1,
      "curveTo": "{0, 1}",
      "hasCurveFrom": false,
      "hasCurveTo": false,
      "point": "{0, 1}"
    },
    {
      "_class": "curvePoint",
      "cornerRadius": 0,
      "curveFrom": "{5.2342318764673682e-05, 0.33330311546248453}",
      "curveMode": 1,
      "curveTo": "{5.2342318764673682e-05, 0.33330311546248453}",
      "hasCurveFrom": false,
      "hasCurveTo": false,
      "point": "{5.2342318764673682e-05, 0.33330311546248453}"
    }
  ],
  "resizingConstraint": 63,
  "resizingType": 0,
  "rotation": 0,
  "shouldBreakMaskChain": false
}